latlon_and_rowcol
