Metadata-Version: 2.2
Name: latlon_and_rowcol
Version: 0.1.3
Summary: 用于风云卫星数据的经纬度和坐标互转
Author: ld
Author-email: 1542864710@qq.com
Keywords: 经纬度,坐标
Classifier: Development Status :: 3 - Alpha
Classifier: License :: OSI Approved :: MIT License
Classifier: Programming Language :: Python :: 3
Classifier: Programming Language :: Python :: 3.11
Classifier: Programming Language :: Python :: 3.12
Classifier: Programming Language :: Python :: 3.8
Classifier: Programming Language :: Python :: 3.9
Classifier: Programming Language :: Python :: 3.10
Dynamic: author
Dynamic: author-email
Dynamic: classifier
Dynamic: description
Dynamic: description-content-type
Dynamic: keywords
Dynamic: summary
